{
  "tabPane": [
    {
      "title": "SmartDashboard",
      "autoPopulate": true,
      "autoPopulatePrefix": "SmartDashboard/",
      "widgetPane": {
        "gridSize": 128.0,
        "showGrid": true,
        "hgap": 16.0,
        "vgap": 16.0,
        "titleType": 0,
        "tiles": {
          "0,0": {
            "size": [
              1,
              1
            ],
            "content": {
              "_type": "Text View",
              "_source0": "network_table:///SmartDashboard/ShooterRPM",
              "_title": "ShooterRPM"
            }
          },
          "1,0": {
            "size": [
              1,
              1
            ],
            "content": {
              "_type": "ComboBox Chooser",
              "_source0": "network_table:///SmartDashboard/Auto Selector",
              "_title": "Auto Selector"
            }
          },
          "2,0": {
            "size": [
              1,
              1
            ],
            "content": {
              "_type": "Text View",
              "_source0": "network_table:///SmartDashboard/Roller Speed",
              "_title": "Roller Speed"
            }
          },
          "3,0": {
            "size": [
              1,
              1
            ],
            "content": {
              "_type": "Text View",
              "_source0": "network_table:///SmartDashboard/TunableNumbers/Primary Shooter/Speed",
              "_title": "TunableNumbers/Primary Shooter/Speed"
            }
          },
          "4,0": {
            "size": [
              1,
              1
            ],
            "content": {
              "_type": "Text View",
              "_source0": "network_table:///SmartDashboard/Odo H",
              "_title": "Odo H"
            }
          },
          "7,0": {
            "size": [
              1,
              1
            ],
            "content": {
              "_type": "Text View",
              "_source0": "network_table:///SmartDashboard/Intake/Four Bar Current Draw",
              "_title": "Intake/Four Bar Current Draw"
            }
          },
          "4,3": {
            "size": [
              1,
              1
            ],
            "content": {
              "_type": "Boolean Box",
              "_source0": "network_table:///SmartDashboard/Lower Sensorz",
              "_title": "Lower Sensorz",
              "Colors/Color when true": "#7CFC00FF",
              "Colors/Color when false": "#8B0000FF"
            }
          },
          "0,1": {
            "size": [
              1,
              1
            ],
            "content": {
              "_type": "Text View",
              "_source0": "network_table:///SmartDashboard/TopShooterRPM",
              "_title": "TopShooterRPM"
            }
          },
          "8,2": {
            "size": [
              2,
              1
            ],
            "content": {
              "_type": "Text View",
              "_source0": "network_table:///SmartDashboard/Climber encoder left",
              "_title": "Climber encoder left"
            }
          },
          "2,1": {
            "size": [
              1,
              1
            ],
            "content": {
              "_type": "Text View",
              "_source0": "network_table:///SmartDashboard/Top error",
              "_title": "Top error"
            }
          },
          "6,3": {
            "size": [
              1,
              1
            ],
            "content": {
              "_type": "Boolean Box",
              "_source0": "network_table:///SmartDashboard/Upper Sensorz",
              "_title": "Upper Sensorz",
              "Colors/Color when true": "#7CFC00FF",
              "Colors/Color when false": "#8B0000FF"
            }
          },
          "4,1": {
            "size": [
              1,
              1
            ],
            "content": {
              "_type": "Text View",
              "_source0": "network_table:///SmartDashboard/Shooter error",
              "_title": "Shooter error"
            }
          },
          "7,1": {
            "size": [
              1,
              1
            ],
            "content": {
              "_type": "Text View",
              "_source0": "network_table:///SmartDashboard/TunableNumbers/Top Shooter/Speed",
              "_title": "TunableNumbers/Top Shooter/Speed"
            }
          },
          "8,1": {
            "size": [
              2,
              1
            ],
            "content": {
              "_type": "Text View",
              "_source0": "network_table:///SmartDashboard/Climber encoder right",
              "_title": "Climber encoder right"
            }
          },
          "0,2": {
            "size": [
              1,
              1
            ],
            "content": {
              "_type": "Text View",
              "_source0": "network_table:///SmartDashboard/Intake/Four Bar Position",
              "_title": "Intake/Four Bar Position"
            }
          },
          "1,2": {
            "size": [
              1,
              1
            ],
            "content": {
              "_type": "Text View",
              "_source0": "network_table:///SmartDashboard/climber speed",
              "_title": "climber speed"
            }
          },
          "2,2": {
            "size": [
              1,
              1
            ],
            "content": {
              "_type": "Text View",
              "_source0": "network_table:///SmartDashboard/ShooterSetpoint",
              "_title": "ShooterSetpoint"
            }
          },
          "5,0": {
            "size": [
              1,
              1
            ],
            "content": {
              "_type": "Text View",
              "_source0": "network_table:///SmartDashboard/Odo X",
              "_title": "Odo X"
            }
          },
          "6,0": {
            "size": [
              1,
              1
            ],
            "content": {
              "_type": "Text View",
              "_source0": "network_table:///SmartDashboard/Odo Y",
              "_title": "Odo Y"
            }
          },
          "8,0": {
            "size": [
              1,
              1
            ],
            "content": {
              "_type": "Text View",
              "_source0": "network_table:///SmartDashboard/Left Enc",
              "_title": "Left Enc"
            }
          },
          "9,0": {
            "size": [
              1,
              1
            ],
            "content": {
              "_type": "Text View",
              "_source0": "network_table:///SmartDashboard/Right Enc",
              "_title": "Right Enc"
            }
          },
          "10,0": {
            "size": [
              1,
              1
            ],
            "content": {
              "_type": "Text View",
              "_source0": "network_table:///SmartDashboard/Intake/Filtered Current",
              "_title": "Intake/Filtered Current"
            }
          },
          "1,1": {
            "size": [
              1,
              1
            ],
            "content": {
              "_type": "Text View",
              "_source0": "network_table:///SmartDashboard/TunableNumbers/Shooter/kP",
              "_title": "TunableNumbers/Shooter/kP"
            }
          }
        }
      }
    },
    {
      "title": "LiveWindow",
      "autoPopulate": true,
      "autoPopulatePrefix": "LiveWindow/",
      "widgetPane": {
        "gridSize": 128.0,
        "showGrid": true,
        "hgap": 16.0,
        "vgap": 16.0,
        "titleType": 0,
        "tiles": {
          "0,0": {
            "size": [
              2,
              4
            ],
            "content": {
              "_type": "Subsystem Layout",
              "_source0": "network_table:///LiveWindow/ShootSubsystem",
              "_title": "ShootSubsystem",
              "Layout/Label position": "BOTTOM",
              "_children": []
            }
          },
          "2,0": {
            "size": [
              2,
              4
            ],
            "content": {
              "_type": "Subsystem Layout",
              "_source0": "network_table:///LiveWindow/Ungrouped",
              "_title": "Ungrouped",
              "Layout/Label position": "BOTTOM",
              "_children": [
                {
                  "_type": "PID Controller",
                  "_source0": "network_table:///LiveWindow/Ungrouped/PIDController[9]",
                  "_title": "PIDController[9]"
                },
                {
                  "_type": "PID Controller",
                  "_source0": "network_table:///LiveWindow/Ungrouped/PIDController[12]",
                  "_title": "PIDController[12]"
                },
                {
                  "_type": "PID Controller",
                  "_source0": "network_table:///LiveWindow/Ungrouped/PIDController[1]",
                  "_title": "PIDController[1]"
                },
                {
                  "_type": "Gyro",
                  "_source0": "network_table:///LiveWindow/Ungrouped/ADXRS450_Gyro[0]",
                  "_title": "ADXRS450_Gyro[0]",
                  "Visuals/Major tick spacing": 45.0,
                  "Visuals/Starting angle": 180.0,
                  "Visuals/Show tick mark ring": true,
                  "Visuals/Counter clockwise": false
                },
                {
                  "_type": "PID Controller",
                  "_source0": "network_table:///LiveWindow/Ungrouped/PIDController[6]",
                  "_title": "PIDController[6]"
                },
                {
                  "_type": "PID Controller",
                  "_source0": "network_table:///LiveWindow/Ungrouped/PIDController[2]",
                  "_title": "PIDController[2]"
                },
                {
                  "_type": "PID Controller",
                  "_source0": "network_table:///LiveWindow/Ungrouped/PIDController[11]",
                  "_title": "PIDController[11]"
                },
                {
                  "_type": "PID Controller",
                  "_source0": "network_table:///LiveWindow/Ungrouped/PIDController[8]",
                  "_title": "PIDController[8]"
                },
                {
                  "_type": "Motor Controller",
                  "_source0": "network_table:///LiveWindow/Ungrouped/Spark[0]",
                  "_title": "Spark[0]",
                  "Visuals/Orientation": "HORIZONTAL"
                },
                {
                  "_type": "PID Controller",
                  "_source0": "network_table:///LiveWindow/Ungrouped/PIDController[3]",
                  "_title": "PIDController[3]"
                },
                {
                  "_type": "PID Controller",
                  "_source0": "network_table:///LiveWindow/Ungrouped/PIDController[7]",
                  "_title": "PIDController[7]"
                },
                {
                  "_type": "Boolean Box",
                  "_source0": "network_table:///LiveWindow/Ungrouped/DigitalInput[3]/Value",
                  "_title": "DigitalInput[3]/Value",
                  "Colors/Color when true": "#7CFC00FF",
                  "Colors/Color when false": "#8B0000FF"
                },
                {
                  "_type": "PID Controller",
                  "_source0": "network_table:///LiveWindow/Ungrouped/PIDController[4]",
                  "_title": "PIDController[4]"
                },
                {
                  "_type": "Text View",
                  "_source0": "network_table:///LiveWindow/Ungrouped/BangBangController[1]/measurement",
                  "_title": "BangBangController[1]/measurement"
                },
                {
                  "_type": "PID Controller",
                  "_source0": "network_table:///LiveWindow/Ungrouped/PIDController[5]",
                  "_title": "PIDController[5]"
                },
                {
                  "_type": "PID Controller",
                  "_source0": "network_table:///LiveWindow/Ungrouped/PIDController[10]",
                  "_title": "PIDController[10]"
                },
                {
                  "_type": "Boolean Box",
                  "_source0": "network_table:///LiveWindow/Ungrouped/DigitalInput[1]/Value",
                  "_title": "DigitalInput[1]/Value",
                  "Colors/Color when true": "#7CFC00FF",
                  "Colors/Color when false": "#8B0000FF"
                },
                {
                  "_type": "Text View",
                  "_source0": "network_table:///LiveWindow/Ungrouped/BangBangController[1]/tolerance",
                  "_title": "BangBangController[1]/tolerance"
                },
                {
                  "_type": "Text View",
                  "_source0": "network_table:///LiveWindow/Ungrouped/BangBangController[1]/setpoint",
                  "_title": "BangBangController[1]/setpoint"
                },
                {
                  "_type": "Text View",
                  "_source0": "network_table:///LiveWindow/Ungrouped/BangBangController[1]/error",
                  "_title": "BangBangController[1]/error"
                },
                {
                  "_type": "Boolean Box",
                  "_source0": "network_table:///LiveWindow/Ungrouped/BangBangController[1]/atSetpoint",
                  "_title": "BangBangController[1]/atSetpoint",
                  "Colors/Color when true": "#7CFC00FF",
                  "Colors/Color when false": "#8B0000FF"
                },
                {
                  "_type": "PID Controller",
                  "_source0": "network_table:///LiveWindow/Ungrouped/PIDController[13]",
                  "_title": "PIDController[13]"
                },
                {
                  "_type": "PID Controller",
                  "_source0": "network_table:///LiveWindow/Ungrouped/PIDController[15]",
                  "_title": "PIDController[15]"
                },
                {
                  "_type": "PID Controller",
                  "_source0": "network_table:///LiveWindow/Ungrouped/PIDController[14]",
                  "_title": "PIDController[14]"
                },
                {
                  "_type": "PID Controller",
                  "_source0": "network_table:///LiveWindow/Ungrouped/PIDController[16]",
                  "_title": "PIDController[16]"
                },
                {
                  "_type": "PID Controller",
                  "_source0": "network_table:///LiveWindow/Ungrouped/PIDController[25]",
                  "_title": "PIDController[25]"
                },
                {
                  "_type": "PID Controller",
                  "_source0": "network_table:///LiveWindow/Ungrouped/PIDController[23]",
                  "_title": "PIDController[23]"
                },
                {
                  "_type": "PID Controller",
                  "_source0": "network_table:///LiveWindow/Ungrouped/PIDController[28]",
                  "_title": "PIDController[28]"
                },
                {
                  "_type": "PID Controller",
                  "_source0": "network_table:///LiveWindow/Ungrouped/PIDController[27]",
                  "_title": "PIDController[27]"
                },
                {
                  "_type": "PID Controller",
                  "_source0": "network_table:///LiveWindow/Ungrouped/PIDController[29]",
                  "_title": "PIDController[29]"
                },
                {
                  "_type": "PID Controller",
                  "_source0": "network_table:///LiveWindow/Ungrouped/PIDController[30]",
                  "_title": "PIDController[30]"
                },
                {
                  "_type": "PID Controller",
                  "_source0": "network_table:///LiveWindow/Ungrouped/PIDController[18]",
                  "_title": "PIDController[18]"
                },
                {
                  "_type": "PID Controller",
                  "_source0": "network_table:///LiveWindow/Ungrouped/PIDController[22]",
                  "_title": "PIDController[22]"
                },
                {
                  "_type": "PID Controller",
                  "_source0": "network_table:///LiveWindow/Ungrouped/PIDController[19]",
                  "_title": "PIDController[19]"
                },
                {
                  "_type": "PID Controller",
                  "_source0": "network_table:///LiveWindow/Ungrouped/PIDController[24]",
                  "_title": "PIDController[24]"
                },
                {
                  "_type": "PID Controller",
                  "_source0": "network_table:///LiveWindow/Ungrouped/PIDController[32]",
                  "_title": "PIDController[32]"
                },
                {
                  "_type": "PID Controller",
                  "_source0": "network_table:///LiveWindow/Ungrouped/PIDController[26]",
                  "_title": "PIDController[26]"
                },
                {
                  "_type": "PID Controller",
                  "_source0": "network_table:///LiveWindow/Ungrouped/PIDController[17]",
                  "_title": "PIDController[17]"
                },
                {
                  "_type": "PID Controller",
                  "_source0": "network_table:///LiveWindow/Ungrouped/PIDController[20]",
                  "_title": "PIDController[20]"
                },
                {
                  "_type": "PID Controller",
                  "_source0": "network_table:///LiveWindow/Ungrouped/PIDController[21]",
                  "_title": "PIDController[21]"
                },
                {
                  "_type": "PID Controller",
                  "_source0": "network_table:///LiveWindow/Ungrouped/PIDController[31]",
                  "_title": "PIDController[31]"
                },
                {
                  "_type": "PID Controller",
                  "_source0": "network_table:///LiveWindow/Ungrouped/PIDController[38]",
                  "_title": "PIDController[38]"
                },
                {
                  "_type": "PID Controller",
                  "_source0": "network_table:///LiveWindow/Ungrouped/PIDController[37]",
                  "_title": "PIDController[37]"
                },
                {
                  "_type": "PID Controller",
                  "_source0": "network_table:///LiveWindow/Ungrouped/PIDController[36]",
                  "_title": "PIDController[36]"
                },
                {
                  "_type": "PID Controller",
                  "_source0": "network_table:///LiveWindow/Ungrouped/PIDController[34]",
                  "_title": "PIDController[34]"
                },
                {
                  "_type": "PID Controller",
                  "_source0": "network_table:///LiveWindow/Ungrouped/PIDController[35]",
                  "_title": "PIDController[35]"
                },
                {
                  "_type": "PID Controller",
                  "_source0": "network_table:///LiveWindow/Ungrouped/PIDController[33]",
                  "_title": "PIDController[33]"
                },
                {
                  "_type": "PID Controller",
                  "_source0": "network_table:///LiveWindow/Ungrouped/PIDController[40]",
                  "_title": "PIDController[40]"
                },
                {
                  "_type": "PID Controller",
                  "_source0": "network_table:///LiveWindow/Ungrouped/PIDController[39]",
                  "_title": "PIDController[39]"
                }
              ]
            }
          },
          "4,0": {
            "size": [
              2,
              4
            ],
            "content": {
              "_type": "Subsystem Layout",
              "_source0": "network_table:///LiveWindow/IntakeSubsystem",
              "_title": "IntakeSubsystem",
              "Layout/Label position": "BOTTOM",
              "_children": []
            }
          },
          "6,0": {
            "size": [
              2,
              4
            ],
            "content": {
              "_type": "Subsystem Layout",
              "_source0": "network_table:///LiveWindow/DriveSubsystem",
              "_title": "DriveSubsystem",
              "Layout/Label position": "BOTTOM",
              "_children": []
            }
          },
          "8,0": {
            "size": [
              2,
              4
            ],
            "content": {
              "_type": "Subsystem Layout",
              "_source0": "network_table:///LiveWindow/IntakeFourBar",
              "_title": "IntakeFourBar",
              "Layout/Label position": "BOTTOM",
              "_children": []
            }
          },
          "0,4": {
            "size": [
              2,
              4
            ],
            "content": {
              "_type": "Subsystem Layout",
              "_source0": "network_table:///LiveWindow/StripSubsystem",
              "_title": "StripSubsystem",
              "Layout/Label position": "BOTTOM",
              "_children": []
            }
          },
          "2,4": {
            "size": [
              2,
              4
            ],
            "content": {
              "_type": "Subsystem Layout",
              "_source0": "network_table:///LiveWindow/ClimberSubsystem",
              "_title": "ClimberSubsystem",
              "Layout/Label position": "BOTTOM",
              "_children": []
            }
          },
          "4,4": {
            "size": [
              2,
              4
            ],
            "content": {
              "_type": "Subsystem Layout",
              "_source0": "network_table:///LiveWindow/SnekSystem",
              "_title": "SnekSystem",
              "Layout/Label position": "BOTTOM",
              "_children": []
            }
          }
        }
      }
    }
  ],
  "windowGeometry": {
    "x": -8.0,
    "y": -8.0,
    "width": 1616.0,
    "height": 876.0
  }
}